pqct/__init__.py
pqct/algorithms.py
pqct/tests.py
pqct/toolkit.py
post_quantum_crypto_toolkit-0.1.0.dist-info/LICENSE
post_quantum_crypto_toolkit-0.1.0.dist-info/METADATA
post_quantum_crypto_toolkit-0.1.0.dist-info/WHEEL
post_quantum_crypto_toolkit-0.1.0.dist-info/top_level.txt
post_quantum_crypto_toolkit-0.1.0.dist-info/RECORD
