Metadata-Version: 2.1
Name: post-quantum-crypto-toolkit
Version: 0.1.0
Summary: A Python toolkit for post-quantum cryptographic algorithms
Home-page: https://github.com/G4G4N/post-quantum-crypto-toolkit
Author: Gagan Yalamuri
Author-email: gagan.y@nyu.com
Classifier: Programming Language :: Python :: 3
Classifier: License :: OSI Approved :: MIT License
Classifier: Operating System :: OS Independent
Requires-Python: >=3.6
License-File: LICENSE
Requires-Dist: pqcrypto
Requires-Dist: numpy
